zinnia_ckeditor/__init__.py
zinnia_ckeditor/admin.py
zinnia_wysiwyg_ckeditor-1.3.dist-info/DESCRIPTION.rst
zinnia_wysiwyg_ckeditor-1.3.dist-info/METADATA
zinnia_wysiwyg_ckeditor-1.3.dist-info/RECORD
zinnia_wysiwyg_ckeditor-1.3.dist-info/WHEEL
zinnia_wysiwyg_ckeditor-1.3.dist-info/metadata.json
zinnia_wysiwyg_ckeditor-1.3.dist-info/top_level.txt
