Metadata-Version: 2.0
Name: zinnia-wysiwyg-ckeditor
Version: 1.3
Summary: CKEditor for editing entries in django-blog-zinnia
Home-page: https://github.com/django-blog-zinnia/zinnia-wysiwyg-ckeditor
Author: Fantomas42
Author-email: fantomas42@gmail.com
License: BSD License
Keywords: django,zinnia,wysiwyg,ckeditor
Platform: UNKNOWN
Classifier: Framework :: Django
Classifier: Development Status :: 5 - Production/Stable
Classifier: Environment :: Web Environment
Classifier: Programming Language :: Python
Classifier: Programming Language :: Python :: 3
Classifier: Intended Audience :: Developers
Classifier: Operating System :: OS Independent
Classifier: License :: OSI Approved :: BSD License
Classifier: Topic :: Software Development :: Libraries :: Python Modules
Requires-Dist: django-ckeditor
